perf_py_pkg/__init__.py
perf_py_pkg/core.py
perf_py_pkg/py.typed
perf_py_pkg/utils.py
perf_py_pkg/value/__init__.py
perf_py_pkg/value/book_to_price.py
perf_py_pkg-0.0.3.dist-info/LICENSE
perf_py_pkg-0.0.3.dist-info/METADATA
perf_py_pkg-0.0.3.dist-info/WHEEL
perf_py_pkg-0.0.3.dist-info/entry_points.txt
perf_py_pkg-0.0.3.dist-info/RECORD
