Metadata-Version: 2.1
Name: perf-py-pkg
Version: 0.0.3
Summary: Perfect Python Package
Home-page: https://github.com/kulsuri/perf-py-pkg
License: MIT
Author: Kulraj Suri
Author-email: kul@outlook.com
Requires-Python: >=3.9,<4.0
Classifier: Development Status :: 5 - Production/Stable
Classifier: License :: OSI Approved :: MIT License
Classifier: Programming Language :: Python :: 3
Classifier: Programming Language :: Python :: 3.9
Classifier: Programming Language :: Python :: 3.10
Classifier: Programming Language :: Python :: 3.11
Project-URL: Changelog, https://github.com/kulsuri/perf-py-pkg/releases
Project-URL: Documentation, https://perf-py-pkg.readthedocs.io
Project-URL: Repository, https://github.com/kulsuri/perf-py-pkg
